langchain_crynux/__init__.py
langchain_crynux/chat_models.py
langchain_crynux-0.1.1.dist-info/licenses/LICENSE
langchain_crynux-0.1.1.dist-info/METADATA
langchain_crynux-0.1.1.dist-info/WHEEL
langchain_crynux-0.1.1.dist-info/top_level.txt
langchain_crynux-0.1.1.dist-info/RECORD
