Metadata-Version: 2.4
Name: langchain-crynux
Version: 0.1.1
Summary: LangChain ChatOpenAI wrapper for Crynux.
License:                                  Apache License
Requires-Python: >=3.9
License-File: LICENSE
Requires-Dist: langchain-openai>=1.0.1
Dynamic: license-file
